{
  "project_info": {
    "project_number": "7372161177",
    "firebase_url": "https://movie-watch-list-d2665.firebaseio.com",
    "project_id": "movie-watch-list-d2665",
    "storage_bucket": "movie-watch-list-d2665.firebasestorage.app"
  },
  "client": [
    {
      "client_info": {
        "mobilesdk_app_id": "1:7372161177:android:44480dff2d0e00c0f7f808",
        "android_client_info": {
          "package_name": "com.cinewatch.cinewatch"
        }
      },
      "oauth_client": [
        {
          "client_id": "7372161177-sj3mvfgkuuq3nlf4ic8o446tbdvsslsb.apps.googleusercontent.com",
          "client_type": 3
        }
      ],
      "api_key": [
        {
          "current_key": "AIzaSyC8QTF7t3pve7zBgs_t5cXMswsF9h9bmbU"
        }
      ],
      "services": {
        "appinvite_service": {
          "other_platform_oauth_client": [
            {
              "client_id": "7372161177-sj3mvfgkuuq3nlf4ic8o446tbdvsslsb.apps.googleusercontent.com",
              "client_type": 3
            }
          ]
        }
      }
    }
  ],
  "configuration_version": "1"
}
